pyrulo/__init__.py
pyrulo/class_imports.py
pyrulo-0.2.7.dist-info/LICENSE
pyrulo-0.2.7.dist-info/METADATA
pyrulo-0.2.7.dist-info/WHEEL
pyrulo-0.2.7.dist-info/top_level.txt
pyrulo-0.2.7.dist-info/RECORD
